{
  "kind": "collectionType",
  "collectionName": "events",
  "info": {
    "singularName": "event",
    "pluralName": "events",
    "displayName": "Event"
  },
  "options": {
    "draftAndPublish": true
  },
  "pluginOptions": {},
  "attributes": {
    "title": {
      "type": "string",
      "required": true
    },
    "slug": {
      "type": "uid",
      "targetField": "title",
      "required": true,
      "unique": true,
      "regex": "^[a-z0-9]+(?:-[a-z0-9]+)*$"
    },
    "startDate": {
      "type": "datetime",
      "required": true
    },
    "endDate": {
      "type": "datetime"
    },
    "timezone": {
      "type": "string"
    },
    "isOnline": {
      "type": "boolean",
      "default": false
    },
    "location": {
      "type": "string"
    },
    "description": {
      "type": "text"
    },
    "registrationUrl": {
      "type": "string"
    },
    "ctaLabel": {
      "type": "string"
    },
    "cover": {
      "type": "media",
      "allowedTypes": [
        "images"
      ],
      "multiple": false
    },
    "heroGallery": {
      "type": "media",
      "multiple": true,
      "allowedTypes": [
        "images"
      ]
    },
    "category": {
      "type": "enumeration",
      "enum": [
        "conference",
        "gathering",
        "outreach",
        "online"
      ],
      "default": "conference"
    },
    "seoTitle": {
      "type": "string"
    },
    "seoDescription": {
      "type": "text"
    },
    "seoImage": {
      "type": "media",
      "allowedTypes": [
        "images"
      ],
      "multiple": false
    }
  }
}
